{
    "code": 200,
    "data": [
        {
            "name": "Murari",
            "label": null,
            "image": null,
            "description": null
        },
        {
            "name": "Murari",
            "label": null,
            "image": null,
            "description": null
        },
        {
            "name": "Murari",
            "label": null,
            "image": null,
            "description": null
        },
        {
            "name": "Murari",
            "label": null,
            "image": null,
            "description": null
        },
        {
            "name": "murari",
            "label": null,
            "image": null,
            "description": null
        },
        {
            "name": "Murari",
            "label": null,
            "image": null,
            "description": null
        },
        {
            "name": "Murari",
            "label": null,
            "image": null,
            "description": null
        },
        {
            "name": "Murari",
            "label": null,
            "image": null,
            "description": null
        }
    ]
}